setup.py
natspec_utils/__init__.py
natspec_utils/decorators.py
natspec_utils/exceptions.py
natspec_utils/match.py
natspec_utils/stringutils.py
natspec_utils/types.py
natspec_utils.egg-info/PKG-INFO
natspec_utils.egg-info/SOURCES.txt
natspec_utils.egg-info/dependency_links.txt
natspec_utils.egg-info/top_level.txt