Metadata-Version: 1.1
Name: natspec-utils
Version: 1.0.2
Summary: Decorators and Utilities needed for NatSpec - A tool for ATDD with natural language
Home-page: http://nat-spec.com
Author: DevBoost GmbH
Author-email: contact@devboost.de
License: EPL
Platform: UNKNOWN
Classifier: Development Status :: 5 - Production/Stable
